pyinlineasm/__init__.py
pyinlineasm-0.0.2.dist-info/METADATA
pyinlineasm-0.0.2.dist-info/WHEEL
pyinlineasm-0.0.2.dist-info/top_level.txt
pyinlineasm-0.0.2.dist-info/RECORD
