Metadata-Version: 2.4
Name: pyinlineasm
Version: 0.0.2
Summary: inline asm for python using keystone
Author-email: Jhonata Rios Carneiro <jhonatacarneirorios432@gmail.com>
Requires-Python: >=3.8
Requires-Dist: keystone-engine>=0.9.2rc1
Requires-Dist: capstone>=5.0.0
